sqlalchemy_hsqldb/__init__.py
sqlalchemy_hsqldb/base.py
sqlalchemy_hsqldb/jaydebeapi.py
sqlalchemy_hsqldb/provision.py
sqlalchemy_hsqldb/requirements.py
sqlalchemy_hsqldb-0.2.1.dist-info/METADATA
sqlalchemy_hsqldb-0.2.1.dist-info/WHEEL
sqlalchemy_hsqldb-0.2.1.dist-info/entry_points.txt
sqlalchemy_hsqldb-0.2.1.dist-info/top_level.txt
sqlalchemy_hsqldb-0.2.1.dist-info/RECORD
