Metadata-Version: 2.4
Name: sqlalchemy-hsqldb
Version: 0.2.1
Summary: SQLAlchemy dialect for HyperSQL 2.0 (HSQLDB)
Home-page: https://github.com/Pebble94464/sqlalchemy-hsqldb
Author: Pebble94464
Author-email: sqlalchemy-hsqldb@pebble.plus.com
License: MIT
Project-URL: Documentation, https://github.com/Pebble94464/sqlalchemy-hsqldb/wiki
Project-URL: Source, https://github.com/Pebble94464/sqlalchemy-hsqldb
Project-URL: Tracker, https://github.com/Pebble94464/sqlalchemy-hsqldb/issues
Keywords: SQLAlchemy dialect hsqld hsqldb hypersql
Classifier: Development Status :: 4 - Beta
Classifier: Intended Audience :: Developers
Classifier: License :: OSI Approved :: MIT License
Classifier: Programming Language :: Python
Classifier: Programming Language :: Python :: 3
Classifier: Topic :: Database :: Front-Ends
Classifier: Operating System :: OS Independent
Requires-Dist: SQLAlchemy
Requires-Dist: jaydebeapi-hsqldb
Dynamic: author
Dynamic: author-email
Dynamic: classifier
Dynamic: description
Dynamic: description-content-type
Dynamic: home-page
Dynamic: keywords
Dynamic: license
Dynamic: project-url
Dynamic: requires-dist
Dynamic: summary
